{
  "ua": "Mozilla/5.0 (iPhone; CPU iPhone OS 13_2_3 like Mac OS X) AppleWebKit/605.1.15 (KHTML, like Gecko) Version/13.0.3 Mobile/15E148 Safari/604.1",
  "homeUrl": "http://www.lezhutv.com",
  "cateNode": "//div[@class='nav']/a[position()>1]",
  "cateName": "/text()",
  "cateId": "/@href",
  "cateIdR": "/type/(\\S+).html", 
  "homeVodNode": "//ul[contains(@class, 'tbox_m')]/li[contains(@class,'vbox')]/a[contains(@class,'vbox_t')]",
  "homeVodName": "/@title",
  "homeVodId": "/@href",
  "homeVodIdR": "/detail/(\\w+).html",
  "homeVodImg": "/@data-original",
  "homeVodImgR": "\\S+(http\\S+)",
  "homeVodMark": "/span/text()",
  "cateUrl": "http://www.lezhutv.com/type/{cateId}-{catePg}.html",
  "cateVodNode": "//ul[contains(@class, 'tbox_m')]/li[contains(@class,'vbox')]/a[contains(@class,'vbox_t')]",
  "cateVodName": "/@title",
  "cateVodId": "/@href",
  "cateVodIdR": "/detail/(\\w+).html",
  "cateVodImg": "/@data-original",
  "cateVodImgR": "\\S+(http\\S+)",
  "cateVodMark": "/span/text()",
  "dtUrl": "http://www.lezhutv.com/detail/{vid}.html",
  "dtNode": "//body",
  "dtName": "//div[@class='data']/h4/text()",
  "dtNameR": "",
  "dtImg": "//div[@class='dbox']/div[contains(@class,'img item-lazy')]/@data-original",
  "dtImgR": "\\S+(http\\S+)",
  "dtCate": "//p[@class='yac']/text()",
  "dtCateR": "/(.+?)/",
  "dtYear": "//p[@class='yac']/text()",
  "dtYearR": "(.+?)-",
  "dtArea": "//p[@class='yac']/text()",
  "dtAreaR": ".+/(.+)",
  "dtMark": "//p[@class='yac']/text()",
  "dtMarkR": ".+?/.+?/(.+?)/.+",
  "dtActor": "//p[@class='act']/text()",
  "dtActorR": "",
  "dtDirector": "//p[@class='dir']/text()",
  "dtDirectorR": "",
  "dtDesc": "//div[@class='tbox_js']/text()",
  "dtDescR": "",
  "dtFromNode": "//div[contains(@class, 'tbox_t')]/h3/i[contains(@class, 'icon-pin')]/parent::*",
  "dtFromName": "concat('播放源',count(parent::*/preceding::*/div[contains(@class, 'tbox_t')]/h3/i[contains(@class, 'icon-pin')]) + 1)",
  "dtFromNameR": "(\\S+).0",
  "dtUrlNode": "//div[contains(@class,'tabs_block')]/ul[contains(@class, 'list_block show')]",
  "dtUrlSubNode": "/li/a",
  "dtUrlId": "@href",
  "dtUrlIdR": "/play/(\\S+).html",
  "dtUrlName": "/text()",
  "dtUrlNameR": "",
  "playUrl": "http://www.lezhutv.com/play/{playUrl}.html",
  "playUa": "",
  "searchUrl": "http://www.lezhutv.com/index.php?m=vod-search&wd={wd}",
  "scVodNode": "//ul[@class='tbox_m']/li/a",
  "scVodName": "/@title",
  "scVodId": "/@href",
  "scVodIdR": "/detail/(\\w+).html",
  "scVodImg": "/@data-original",
  "scVodMark": "/span/text()"
}
